structured_config/__init__.py
structured_config/configfile.py
structured_config/containers.py
structured_config/fields.py
structured_config/meta.py
structured_config/serialise.py
structured_config-4.12.dist-info/LICENSE
structured_config-4.12.dist-info/METADATA
structured_config-4.12.dist-info/WHEEL
structured_config-4.12.dist-info/top_level.txt
structured_config-4.12.dist-info/RECORD
