Metadata-Version: 2.1
Name: structured-config
Version: 4.12
Summary: Configuration module for python where the config structure is solely defined in python with full autocomplete support.
Home-page: https://gitlab.com/alelec/structured_config
Author: Andrew Leech
Author-email: andrew@alelec.net
License: MIT
Platform: UNKNOWN
Requires-Dist: setuptools
Requires-Dist: setuptools-scm
Requires-Dist: PyYAML
Requires-Dist: wrapt
Requires-Dist: appdirs
Requires-Dist: aenum
Requires-Dist: cryptography
